forged/__init__.py
forged/misc.py
forged-0.0.3.dist-info/LICENSE
forged-0.0.3.dist-info/METADATA
forged-0.0.3.dist-info/WHEEL
forged-0.0.3.dist-info/top_level.txt
forged-0.0.3.dist-info/RECORD
