Metadata-Version: 2.1
Name: forged
Version: 0.0.3
Summary: Tools for data generation
Home-page: https://github.com/otosense/forged
Author: OtoSense
License: apache-2.0
Keywords: data generation,synthetic data,feature vectors
Platform: any
Requires-Dist: scikit-learn
Requires-Dist: numpy
